LICENSE.txt
MANIFEST.in
README.md
VERSION
setup.py
mdexecod.egg-info/PKG-INFO
mdexecod.egg-info/SOURCES.txt
mdexecod.egg-info/dependency_links.txt
mdexecod.egg-info/top_level.txt
src/__init__.py
src/execond/__init__.py
src/execond/main.py