Metadata-Version: 2.1
Name: mdexecod
Version: 0.0.4
Summary: mdexecod
Home-page: https://illustria.io
Author: Bogdan Kortnov
Author-email: bogdan@illustria.io
License: MIT
Platform: UNKNOWN
License-File: LICENSE.txt
